{"id":"arrow.js","dependencies":[{"name":"/Users/heshamadel/Desktop/codingMath/movingArrow/package.json","includedInParent":true,"mtime":1537584318236}],"generated":{"js":"\nvar Arrow = function Arrow(_ref) {\n  var canvescanvesContext = _ref.canvescanvesContext,\n      arrowPositionX = _ref.arrowPositionX,\n      arrowPositionY = _ref.arrowPositionY;\n\n\n  if (!canvesContext) {\n    throw new ReferenceError('You must provide a canvesContext');\n  }\n\n  this.angle = 0;\n  this.canvescanvesContext = canvescanvesContext;\n  this.arrowPositionX = arrowPositionX;\n  this.arrowPositionY = arrowPositionY;\n};\n\nArrow.prototype.moveTailTo = function (_ref2) {\n  var x = _ref2.x,\n      y = _ref2.y;\n\n\n  arrowPositionX = x;\n  arrowPositionY = y;\n};\n\nArrow.prototype.pointTowards = function (_ref3) {\n  var x = _ref3.x,\n      y = _ref3.y;\n\n\n  var opposite = x - arrowPositionX;\n  var adjusent = y - arrowPositionY;\n  self.angle = Math.atan2(adjusent, opposite);\n};\n\nArrow.prototype.render = function () {\n\n  var self = this;\n  canvesContext.clearRect(0, 0, innerWidth, innerHeight);\n  canvesContext.save();\n  canvesContext.translate(arrowPositionX, arrowPositionY);\n  canvesContext.rotate(self.angle);\n\n  canvesContext.beginPath();\n  canvesContext.moveTo(20, 0);\n  canvesContext.lineTo(-20, 0);\n  canvesContext.moveTo(20, 0);\n  canvesContext.lineTo(10, 10);\n  canvesContext.moveTo(20, 0);\n  canvesContext.lineTo(10, -10);\n  canvesContext.stroke();\n\n  canvesContext.restore();\n\n  requestAnimationFrame(Arrow.prototype.render);\n};\n\nmodule.exports = Arrow;","map":{"mappings":[{"generated":{"line":2,"column":0},"source":"arrow.js","original":{"line":2,"column":0}},{"name":"Arrow","generated":{"line":2,"column":4},"source":"arrow.js","original":{"line":2,"column":6}},{"generated":{"line":2,"column":12},"source":"arrow.js","original":{"line":2,"column":14}},{"name":"Arrow","generated":{"line":2,"column":21},"source":"arrow.js","original":{"line":2,"column":6}},{"generated":{"line":2,"column":26},"source":"arrow.js","original":{"line":2,"column":14}},{"generated":{"line":2,"column":33},"source":"arrow.js","original":{"line":2,"column":79}},{"generated":{"line":3,"column":0},"source":"arrow.js","original":{"line":2,"column":79}},{"name":"canvescanvesContext","generated":{"line":3,"column":6},"source":"arrow.js","original":{"line":2,"column":25}},{"generated":{"line":3,"column":25},"source":"arrow.js","original":{"line":2,"column":79}},{"name":"canvescanvesContext","generated":{"line":3,"column":33},"source":"arrow.js","original":{"line":2,"column":25}},{"generated":{"line":3,"column":52},"source":"arrow.js","original":{"line":2,"column":79}},{"generated":{"line":4,"column":0},"source":"arrow.js","original":{"line":2,"column":79}},{"name":"arrowPositionX","generated":{"line":4,"column":6},"source":"arrow.js","original":{"line":2,"column":46}},{"generated":{"line":4,"column":20},"source":"arrow.js","original":{"line":2,"column":79}},{"name":"arrowPositionX","generated":{"line":4,"column":28},"source":"arrow.js","original":{"line":2,"column":46}},{"generated":{"line":4,"column":42},"source":"arrow.js","original":{"line":2,"column":79}},{"generated":{"line":5,"column":0},"source":"arrow.js","original":{"line":2,"column":79}},{"name":"arrowPositionY","generated":{"line":5,"column":6},"source":"arrow.js","original":{"line":2,"column":62}},{"generated":{"line":5,"column":20},"source":"arrow.js","original":{"line":2,"column":79}},{"name":"arrowPositionY","generated":{"line":5,"column":28},"source":"arrow.js","original":{"line":2,"column":62}},{"generated":{"line":5,"column":42},"source":"arrow.js","original":{"line":2,"column":79}},{"generated":{"line":8,"column":0},"source":"arrow.js","original":{"line":4,"column":2}},{"generated":{"line":8,"column":6},"source":"arrow.js","original":{"line":4,"column":6}},{"name":"canvesContext","generated":{"line":8,"column":7},"source":"arrow.js","original":{"line":4,"column":7}},{"generated":{"line":8,"column":20},"source":"arrow.js","original":{"line":4,"column":2}},{"generated":{"line":8,"column":22},"source":"arrow.js","original":{"line":4,"column":22}},{"generated":{"line":9,"column":0},"source":"arrow.js","original":{"line":5,"column":4}},{"generated":{"line":9,"column":10},"source":"arrow.js","original":{"line":5,"column":10}},{"name":"ReferenceError","generated":{"line":9,"column":14},"source":"arrow.js","original":{"line":5,"column":14}},{"generated":{"line":9,"column":28},"source":"arrow.js","original":{"line":5,"column":10}},{"generated":{"line":9,"column":29},"source":"arrow.js","original":{"line":5,"column":29}},{"generated":{"line":9,"column":63},"source":"arrow.js","original":{"line":5,"column":10}},{"generated":{"line":9,"column":64},"source":"arrow.js","original":{"line":5,"column":4}},{"generated":{"line":10,"column":0},"source":"arrow.js","original":{"line":6,"column":3}},{"generated":{"line":12,"column":0},"source":"arrow.js","original":{"line":8,"column":2}},{"name":"angle","generated":{"line":12,"column":7},"source":"arrow.js","original":{"line":8,"column":7}},{"generated":{"line":12,"column":12},"source":"arrow.js","original":{"line":8,"column":2}},{"generated":{"line":12,"column":15},"source":"arrow.js","original":{"line":8,"column":15}},{"generated":{"line":12,"column":16},"source":"arrow.js","original":{"line":8,"column":2}},{"generated":{"line":13,"column":0},"source":"arrow.js","original":{"line":9,"column":2}},{"name":"canvescanvesContext","generated":{"line":13,"column":7},"source":"arrow.js","original":{"line":9,"column":7}},{"generated":{"line":13,"column":26},"source":"arrow.js","original":{"line":9,"column":2}},{"name":"canvescanvesContext","generated":{"line":13,"column":29},"source":"arrow.js","original":{"line":9,"column":29}},{"generated":{"line":13,"column":48},"source":"arrow.js","original":{"line":9,"column":2}},{"generated":{"line":14,"column":0},"source":"arrow.js","original":{"line":10,"column":2}},{"name":"arrowPositionX","generated":{"line":14,"column":7},"source":"arrow.js","original":{"line":10,"column":7}},{"generated":{"line":14,"column":21},"source":"arrow.js","original":{"line":10,"column":2}},{"name":"arrowPositionX","generated":{"line":14,"column":24},"source":"arrow.js","original":{"line":10,"column":24}},{"generated":{"line":14,"column":38},"source":"arrow.js","original":{"line":10,"column":2}},{"generated":{"line":15,"column":0},"source":"arrow.js","original":{"line":11,"column":2}},{"name":"arrowPositionY","generated":{"line":15,"column":7},"source":"arrow.js","original":{"line":11,"column":7}},{"generated":{"line":15,"column":21},"source":"arrow.js","original":{"line":11,"column":2}},{"name":"arrowPositionY","generated":{"line":15,"column":24},"source":"arrow.js","original":{"line":11,"column":24}},{"generated":{"line":15,"column":38},"source":"arrow.js","original":{"line":11,"column":2}},{"generated":{"line":16,"column":0},"source":"arrow.js","original":{"line":13,"column":1}},{"generated":{"line":16,"column":1},"source":"arrow.js","original":{"line":2,"column":0}},{"name":"Arrow","generated":{"line":18,"column":0},"source":"arrow.js","original":{"line":16,"column":0}},{"name":"prototype","generated":{"line":18,"column":6},"source":"arrow.js","original":{"line":16,"column":6}},{"generated":{"line":18,"column":15},"source":"arrow.js","original":{"line":16,"column":0}},{"name":"moveTailTo","generated":{"line":18,"column":16},"source":"arrow.js","original":{"line":16,"column":16}},{"generated":{"line":18,"column":26},"source":"arrow.js","original":{"line":16,"column":0}},{"generated":{"line":18,"column":29},"source":"arrow.js","original":{"line":16,"column":29}},{"generated":{"line":18,"column":46},"source":"arrow.js","original":{"line":16,"column":46}},{"generated":{"line":19,"column":0},"source":"arrow.js","original":{"line":16,"column":46}},{"name":"x","generated":{"line":19,"column":6},"source":"arrow.js","original":{"line":16,"column":39}},{"generated":{"line":19,"column":7},"source":"arrow.js","original":{"line":16,"column":46}},{"name":"x","generated":{"line":19,"column":16},"source":"arrow.js","original":{"line":16,"column":39}},{"generated":{"line":19,"column":17},"source":"arrow.js","original":{"line":16,"column":46}},{"generated":{"line":20,"column":0},"source":"arrow.js","original":{"line":16,"column":46}},{"name":"y","generated":{"line":20,"column":6},"source":"arrow.js","original":{"line":16,"column":42}},{"generated":{"line":20,"column":7},"source":"arrow.js","original":{"line":16,"column":46}},{"name":"y","generated":{"line":20,"column":16},"source":"arrow.js","original":{"line":16,"column":42}},{"generated":{"line":20,"column":17},"source":"arrow.js","original":{"line":16,"column":46}},{"name":"arrowPositionX","generated":{"line":23,"column":0},"source":"arrow.js","original":{"line":18,"column":2}},{"name":"x","generated":{"line":23,"column":19},"source":"arrow.js","original":{"line":18,"column":19}},{"generated":{"line":23,"column":20},"source":"arrow.js","original":{"line":18,"column":2}},{"name":"arrowPositionY","generated":{"line":24,"column":0},"source":"arrow.js","original":{"line":19,"column":2}},{"name":"y","generated":{"line":24,"column":19},"source":"arrow.js","original":{"line":19,"column":19}},{"generated":{"line":24,"column":20},"source":"arrow.js","original":{"line":19,"column":2}},{"generated":{"line":25,"column":0},"source":"arrow.js","original":{"line":21,"column":1}},{"generated":{"line":25,"column":1},"source":"arrow.js","original":{"line":16,"column":0}},{"name":"Arrow","generated":{"line":27,"column":0},"source":"arrow.js","original":{"line":24,"column":0}},{"name":"prototype","generated":{"line":27,"column":6},"source":"arrow.js","original":{"line":24,"column":6}},{"generated":{"line":27,"column":15},"source":"arrow.js","original":{"line":24,"column":0}},{"name":"pointTowards","generated":{"line":27,"column":16},"source":"arrow.js","original":{"line":24,"column":16}},{"generated":{"line":27,"column":28},"source":"arrow.js","original":{"line":24,"column":0}},{"generated":{"line":27,"column":31},"source":"arrow.js","original":{"line":24,"column":31}},{"generated":{"line":27,"column":48},"source":"arrow.js","original":{"line":24,"column":48}},{"generated":{"line":28,"column":0},"source":"arrow.js","original":{"line":24,"column":48}},{"name":"x","generated":{"line":28,"column":6},"source":"arrow.js","original":{"line":24,"column":41}},{"generated":{"line":28,"column":7},"source":"arrow.js","original":{"line":24,"column":48}},{"name":"x","generated":{"line":28,"column":16},"source":"arrow.js","original":{"line":24,"column":41}},{"generated":{"line":28,"column":17},"source":"arrow.js","original":{"line":24,"column":48}},{"generated":{"line":29,"column":0},"source":"arrow.js","original":{"line":24,"column":48}},{"name":"y","generated":{"line":29,"column":6},"source":"arrow.js","original":{"line":24,"column":44}},{"generated":{"line":29,"column":7},"source":"arrow.js","original":{"line":24,"column":48}},{"name":"y","generated":{"line":29,"column":16},"source":"arrow.js","original":{"line":24,"column":44}},{"generated":{"line":29,"column":17},"source":"arrow.js","original":{"line":24,"column":48}},{"generated":{"line":32,"column":0},"source":"arrow.js","original":{"line":26,"column":2}},{"name":"opposite","generated":{"line":32,"column":6},"source":"arrow.js","original":{"line":26,"column":8}},{"name":"x","generated":{"line":32,"column":17},"source":"arrow.js","original":{"line":26,"column":19}},{"name":"arrowPositionX","generated":{"line":32,"column":21},"source":"arrow.js","original":{"line":26,"column":23}},{"generated":{"line":32,"column":35},"source":"arrow.js","original":{"line":26,"column":2}},{"generated":{"line":33,"column":0},"source":"arrow.js","original":{"line":27,"column":2}},{"name":"adjusent","generated":{"line":33,"column":6},"source":"arrow.js","original":{"line":27,"column":8}},{"name":"y","generated":{"line":33,"column":17},"source":"arrow.js","original":{"line":27,"column":19}},{"name":"arrowPositionY","generated":{"line":33,"column":21},"source":"arrow.js","original":{"line":27,"column":23}},{"generated":{"line":33,"column":35},"source":"arrow.js","original":{"line":27,"column":2}},{"name":"self","generated":{"line":34,"column":0},"source":"arrow.js","original":{"line":28,"column":2}},{"name":"angle","generated":{"line":34,"column":7},"source":"arrow.js","original":{"line":28,"column":7}},{"generated":{"line":34,"column":12},"source":"arrow.js","original":{"line":28,"column":2}},{"name":"Math","generated":{"line":34,"column":15},"source":"arrow.js","original":{"line":28,"column":15}},{"name":"atan2","generated":{"line":34,"column":20},"source":"arrow.js","original":{"line":28,"column":20}},{"generated":{"line":34,"column":25},"source":"arrow.js","original":{"line":28,"column":15}},{"name":"adjusent","generated":{"line":34,"column":26},"source":"arrow.js","original":{"line":28,"column":26}},{"generated":{"line":34,"column":34},"source":"arrow.js","original":{"line":28,"column":15}},{"name":"opposite","generated":{"line":34,"column":36},"source":"arrow.js","original":{"line":28,"column":36}},{"generated":{"line":34,"column":44},"source":"arrow.js","original":{"line":28,"column":15}},{"generated":{"line":34,"column":45},"source":"arrow.js","original":{"line":28,"column":2}},{"generated":{"line":35,"column":0},"source":"arrow.js","original":{"line":30,"column":1}},{"generated":{"line":35,"column":1},"source":"arrow.js","original":{"line":24,"column":0}},{"name":"Arrow","generated":{"line":37,"column":0},"source":"arrow.js","original":{"line":33,"column":0}},{"name":"prototype","generated":{"line":37,"column":6},"source":"arrow.js","original":{"line":33,"column":6}},{"generated":{"line":37,"column":15},"source":"arrow.js","original":{"line":33,"column":0}},{"name":"render","generated":{"line":37,"column":16},"source":"arrow.js","original":{"line":33,"column":16}},{"generated":{"line":37,"column":22},"source":"arrow.js","original":{"line":33,"column":0}},{"generated":{"line":37,"column":25},"source":"arrow.js","original":{"line":33,"column":25}},{"generated":{"line":37,"column":37},"source":"arrow.js","original":{"line":33,"column":36}},{"generated":{"line":39,"column":0},"source":"arrow.js","original":{"line":35,"column":2}},{"name":"self","generated":{"line":39,"column":6},"source":"arrow.js","original":{"line":35,"column":8}},{"generated":{"line":39,"column":13},"source":"arrow.js","original":{"line":35,"column":15}},{"generated":{"line":39,"column":17},"source":"arrow.js","original":{"line":35,"column":2}},{"name":"canvesContext","generated":{"line":40,"column":0},"source":"arrow.js","original":{"line":36,"column":2}},{"name":"clearRect","generated":{"line":40,"column":16},"source":"arrow.js","original":{"line":36,"column":16}},{"generated":{"line":40,"column":25},"source":"arrow.js","original":{"line":36,"column":2}},{"generated":{"line":40,"column":26},"source":"arrow.js","original":{"line":36,"column":26}},{"generated":{"line":40,"column":27},"source":"arrow.js","original":{"line":36,"column":2}},{"generated":{"line":40,"column":29},"source":"arrow.js","original":{"line":36,"column":29}},{"generated":{"line":40,"column":30},"source":"arrow.js","original":{"line":36,"column":2}},{"name":"innerWidth","generated":{"line":40,"column":32},"source":"arrow.js","original":{"line":36,"column":32}},{"generated":{"line":40,"column":42},"source":"arrow.js","original":{"line":36,"column":2}},{"name":"innerHeight","generated":{"line":40,"column":44},"source":"arrow.js","original":{"line":36,"column":44}},{"generated":{"line":40,"column":55},"source":"arrow.js","original":{"line":36,"column":2}},{"name":"canvesContext","generated":{"line":41,"column":0},"source":"arrow.js","original":{"line":37,"column":2}},{"name":"save","generated":{"line":41,"column":16},"source":"arrow.js","original":{"line":37,"column":16}},{"generated":{"line":41,"column":20},"source":"arrow.js","original":{"line":37,"column":2}},{"name":"canvesContext","generated":{"line":42,"column":0},"source":"arrow.js","original":{"line":38,"column":2}},{"name":"translate","generated":{"line":42,"column":16},"source":"arrow.js","original":{"line":38,"column":16}},{"generated":{"line":42,"column":25},"source":"arrow.js","original":{"line":38,"column":2}},{"name":"arrowPositionX","generated":{"line":42,"column":26},"source":"arrow.js","original":{"line":38,"column":26}},{"generated":{"line":42,"column":40},"source":"arrow.js","original":{"line":38,"column":2}},{"name":"arrowPositionY","generated":{"line":42,"column":42},"source":"arrow.js","original":{"line":38,"column":42}},{"generated":{"line":42,"column":56},"source":"arrow.js","original":{"line":38,"column":2}},{"name":"canvesContext","generated":{"line":43,"column":0},"source":"arrow.js","original":{"line":39,"column":2}},{"name":"rotate","generated":{"line":43,"column":16},"source":"arrow.js","original":{"line":39,"column":16}},{"generated":{"line":43,"column":22},"source":"arrow.js","original":{"line":39,"column":2}},{"name":"self","generated":{"line":43,"column":23},"source":"arrow.js","original":{"line":39,"column":23}},{"name":"angle","generated":{"line":43,"column":28},"source":"arrow.js","original":{"line":39,"column":28}},{"generated":{"line":43,"column":33},"source":"arrow.js","original":{"line":39,"column":2}},{"name":"canvesContext","generated":{"line":45,"column":0},"source":"arrow.js","original":{"line":41,"column":2}},{"name":"beginPath","generated":{"line":45,"column":16},"source":"arrow.js","original":{"line":41,"column":16}},{"generated":{"line":45,"column":25},"source":"arrow.js","original":{"line":41,"column":2}},{"name":"canvesContext","generated":{"line":46,"column":0},"source":"arrow.js","original":{"line":42,"column":2}},{"name":"moveTo","generated":{"line":46,"column":16},"source":"arrow.js","original":{"line":42,"column":16}},{"generated":{"line":46,"column":22},"source":"arrow.js","original":{"line":42,"column":2}},{"generated":{"line":46,"column":23},"source":"arrow.js","original":{"line":42,"column":23}},{"generated":{"line":46,"column":25},"source":"arrow.js","original":{"line":42,"column":2}},{"generated":{"line":46,"column":27},"source":"arrow.js","original":{"line":42,"column":27}},{"generated":{"line":46,"column":28},"source":"arrow.js","original":{"line":42,"column":2}},{"name":"canvesContext","generated":{"line":47,"column":0},"source":"arrow.js","original":{"line":43,"column":2}},{"name":"lineTo","generated":{"line":47,"column":16},"source":"arrow.js","original":{"line":43,"column":16}},{"generated":{"line":47,"column":22},"source":"arrow.js","original":{"line":43,"column":2}},{"generated":{"line":47,"column":23},"source":"arrow.js","original":{"line":43,"column":23}},{"generated":{"line":47,"column":24},"source":"arrow.js","original":{"line":43,"column":24}},{"generated":{"line":47,"column":26},"source":"arrow.js","original":{"line":43,"column":2}},{"generated":{"line":47,"column":28},"source":"arrow.js","original":{"line":43,"column":28}},{"generated":{"line":47,"column":29},"source":"arrow.js","original":{"line":43,"column":2}},{"name":"canvesContext","generated":{"line":48,"column":0},"source":"arrow.js","original":{"line":44,"column":2}},{"name":"moveTo","generated":{"line":48,"column":16},"source":"arrow.js","original":{"line":44,"column":16}},{"generated":{"line":48,"column":22},"source":"arrow.js","original":{"line":44,"column":2}},{"generated":{"line":48,"column":23},"source":"arrow.js","original":{"line":44,"column":23}},{"generated":{"line":48,"column":25},"source":"arrow.js","original":{"line":44,"column":2}},{"generated":{"line":48,"column":27},"source":"arrow.js","original":{"line":44,"column":27}},{"generated":{"line":48,"column":28},"source":"arrow.js","original":{"line":44,"column":2}},{"name":"canvesContext","generated":{"line":49,"column":0},"source":"arrow.js","original":{"line":45,"column":2}},{"name":"lineTo","generated":{"line":49,"column":16},"source":"arrow.js","original":{"line":45,"column":16}},{"generated":{"line":49,"column":22},"source":"arrow.js","original":{"line":45,"column":2}},{"generated":{"line":49,"column":23},"source":"arrow.js","original":{"line":45,"column":23}},{"generated":{"line":49,"column":25},"source":"arrow.js","original":{"line":45,"column":2}},{"generated":{"line":49,"column":27},"source":"arrow.js","original":{"line":45,"column":27}},{"generated":{"line":49,"column":29},"source":"arrow.js","original":{"line":45,"column":2}},{"name":"canvesContext","generated":{"line":50,"column":0},"source":"arrow.js","original":{"line":46,"column":2}},{"name":"moveTo","generated":{"line":50,"column":16},"source":"arrow.js","original":{"line":46,"column":16}},{"generated":{"line":50,"column":22},"source":"arrow.js","original":{"line":46,"column":2}},{"generated":{"line":50,"column":23},"source":"arrow.js","original":{"line":46,"column":23}},{"generated":{"line":50,"column":25},"source":"arrow.js","original":{"line":46,"column":2}},{"generated":{"line":50,"column":27},"source":"arrow.js","original":{"line":46,"column":27}},{"generated":{"line":50,"column":28},"source":"arrow.js","original":{"line":46,"column":2}},{"name":"canvesContext","generated":{"line":51,"column":0},"source":"arrow.js","original":{"line":47,"column":2}},{"name":"lineTo","generated":{"line":51,"column":16},"source":"arrow.js","original":{"line":47,"column":16}},{"generated":{"line":51,"column":22},"source":"arrow.js","original":{"line":47,"column":2}},{"generated":{"line":51,"column":23},"source":"arrow.js","original":{"line":47,"column":23}},{"generated":{"line":51,"column":25},"source":"arrow.js","original":{"line":47,"column":2}},{"generated":{"line":51,"column":27},"source":"arrow.js","original":{"line":47,"column":27}},{"generated":{"line":51,"column":28},"source":"arrow.js","original":{"line":47,"column":28}},{"generated":{"line":51,"column":30},"source":"arrow.js","original":{"line":47,"column":2}},{"name":"canvesContext","generated":{"line":52,"column":0},"source":"arrow.js","original":{"line":48,"column":2}},{"name":"stroke","generated":{"line":52,"column":16},"source":"arrow.js","original":{"line":48,"column":16}},{"generated":{"line":52,"column":22},"source":"arrow.js","original":{"line":48,"column":2}},{"name":"canvesContext","generated":{"line":54,"column":0},"source":"arrow.js","original":{"line":50,"column":2}},{"name":"restore","generated":{"line":54,"column":16},"source":"arrow.js","original":{"line":50,"column":16}},{"generated":{"line":54,"column":23},"source":"arrow.js","original":{"line":50,"column":2}},{"name":"requestAnimationFrame","generated":{"line":56,"column":0},"source":"arrow.js","original":{"line":52,"column":2}},{"name":"Arrow","generated":{"line":56,"column":24},"source":"arrow.js","original":{"line":52,"column":24}},{"name":"prototype","generated":{"line":56,"column":30},"source":"arrow.js","original":{"line":52,"column":30}},{"generated":{"line":56,"column":39},"source":"arrow.js","original":{"line":52,"column":24}},{"name":"render","generated":{"line":56,"column":40},"source":"arrow.js","original":{"line":52,"column":40}},{"generated":{"line":56,"column":46},"source":"arrow.js","original":{"line":52,"column":2}},{"generated":{"line":57,"column":0},"source":"arrow.js","original":{"line":54,"column":1}},{"generated":{"line":57,"column":1},"source":"arrow.js","original":{"line":33,"column":0}},{"name":"module","generated":{"line":59,"column":0},"source":"arrow.js","original":{"line":57,"column":0}},{"name":"exports","generated":{"line":59,"column":7},"source":"arrow.js","original":{"line":57,"column":7}},{"generated":{"line":59,"column":14},"source":"arrow.js","original":{"line":57,"column":0}},{"name":"Arrow","generated":{"line":59,"column":17},"source":"arrow.js","original":{"line":57,"column":17}},{"generated":{"line":59,"column":22},"source":"arrow.js","original":{"line":57,"column":0}}],"sources":{"arrow.js":"\nconst Arrow = function ({canvescanvesContext, arrowPositionX, arrowPositionY}) {\n\n  if (!canvesContext) {\n    throw new ReferenceError('You must provide a canvesContext');\n  }\n  \n  this.angle = 0;\n  this.canvescanvesContext = canvescanvesContext;\n  this.arrowPositionX = arrowPositionX;\n  this.arrowPositionY = arrowPositionY\n\n};\n\n\nArrow.prototype.moveTailTo = function({x, y}) {\n\n  arrowPositionX = x;\n  arrowPositionY = y;\n\n};\n\n\nArrow.prototype.pointTowards = function({x, y}) {\n\n  const opposite = x - arrowPositionX;\n  const adjusent = y - arrowPositionY;\n  self.angle = Math.atan2(adjusent, opposite);\n\n};\n\n\nArrow.prototype.render = function() {\n\n  const self = this;\n  canvesContext.clearRect(0, 0, innerWidth, innerHeight);\n  canvesContext.save();\n  canvesContext.translate(arrowPositionX, arrowPositionY);\n  canvesContext.rotate(self.angle);\n\n  canvesContext.beginPath();\n  canvesContext.moveTo(20, 0);\n  canvesContext.lineTo(-20, 0);\n  canvesContext.moveTo(20, 0);\n  canvesContext.lineTo(10, 10);\n  canvesContext.moveTo(20, 0);\n  canvesContext.lineTo(10, -10);\n  canvesContext.stroke();\n\n  canvesContext.restore();\n\n  requestAnimationFrame(Arrow.prototype.render);\n\n};\n\n\nmodule.exports = Arrow;"},"lineCount":null}},"hash":"8ce88ff7e95cd6208594d0e143026dfb","cacheData":{"env":{}}}